irtdata/DDTFile.py
irtdata/FLIR.py
irtdata/__init__.py
irtdata/face_detection.py
irtdata/image_utils.py
irtdata/__pycache__/DDTFile.cpython-39.pyc
irtdata/__pycache__/FLIR.cpython-39.pyc
irtdata/__pycache__/__init__.cpython-39.pyc
irtdata/__pycache__/face_detection.cpython-39.pyc
irtdata/__pycache__/image_utils.cpython-39.pyc
irt_data_utils-0.0.1a2.dist-info/LICENSE
irt_data_utils-0.0.1a2.dist-info/METADATA
irt_data_utils-0.0.1a2.dist-info/WHEEL
irt_data_utils-0.0.1a2.dist-info/top_level.txt
irt_data_utils-0.0.1a2.dist-info/RECORD
